pyconstantt/__init__.py
pyconstantt/constant.py
pyconstantt/example/__init__.py
pyconstantt/example/example.py
pyconstantt-1.0.1.dist-info/LICENSE.txt
pyconstantt-1.0.1.dist-info/METADATA
pyconstantt-1.0.1.dist-info/WHEEL
pyconstantt-1.0.1.dist-info/top_level.txt
pyconstantt-1.0.1.dist-info/RECORD
