Metadata-Version: 2.1
Name: pyconstantt
Version: 1.0.1
Summary: New way to make constant in Python
Home-page: https://github.com/yoonhero/pyconstant
Author: Yoonhero06
Author-email: yoonhero06@naver.com
License: MIT
Keywords: constant final variable
Platform: UNKNOWN
Classifier: License :: OSI Approved :: MIT License
Classifier: Programming Language :: Python :: 3
